lab1-1/ha.v
module  ha(a, b, sum, cout);
// input and output interface
input a, b;
output sum, cout;

// structural modeling

xor u1 (sum, a, b);
and u2 (cout, a, b);

endmodule

lab1-1/fa.v
`include "ha.v"
module fa(a, b, ci, sum, cout);
// input and output declaration
input  a, b, ci;
output sum, cout;

// wire and reg declaration

wire s1, c1, c2;

// module instance

ha ha1 (.a(a), .b(b), .sum(s1), .cout(c1));
ha ha2 (.a(s1), .b(ci), .sum(sum), .cout(c2));

or u1(cout, c1, c2);

endmodule

lab1-1/fa_test.v
`timescale  1ns/10ps
`include "fa.v"
module fa_test;
`define cycle 5

// wire and reg
reg clk;
reg a, b, ci;
wire sum, cout;

// clock gen
initial  clk = 0;
always #(`cycle/2) clk = ~clk;

// design module
fa i_fa(.a(a), .b(b), .ci(ci), .sum(sum), .cout(cout));

// test pattern
initial
a = 1'b0;
b = 1'b0;
ci = 1'b0;
begin
	@(posedge clk)
		a = 1'b0;
		b = 1'b0;
		ci = 1'b0;
		@(posedge clk)
			if ((sum != 0)|(cout != 0)|(sum===1'bz)|(cout===1'bz)|(sum===1'bx)|(cout===1'bx)) begin 
			$display($time, ,"a=%b, b=%b, ci=%b, sum=%b, cout=%b,  ERROR!!!", a,b,ci,sum,cout);  $finish; end
	@(posedge clk)
		a = 1'b0;
		b = 1'b0;
		ci = 1'b1;
		@(posedge clk)
			if ((sum != 1)|(cout != 0)|(sum===1'bz)|(cout===1'bz)|(sum===1'bx)|(cout===1'bx)) begin 
			$display($time, ,"a=%b, b=%b, ci=%b, sum=%b, cout=%b,  ERROR!!!", a,b,ci,sum,cout);  $finish; end
	@(posedge clk)
		a = 1'b0;
		b = 1'b1;
		ci = 1'b0;
		@(posedge clk)
			if ((sum != 1)|(cout != 0)|(sum===1'bz)|(cout===1'bz)|(sum===1'bx)|(cout===1'bx)) begin 
			$display($time, ,"a=%b, b=%b, ci=%b, sum=%b, cout=%b,  ERROR!!!", a,b,ci,sum,cout);  $finish; end
	@(posedge clk)
		a = 1'b0;
		b = 1'b1;
		ci = 1'b1;
		@(posedge clk)
			if ((sum != 0)|(cout != 1)|(sum===1'bz)|(cout===1'bz)|(sum===1'bx)|(cout===1'bx)) begin 
			$display($time, ,"a=%b, b=%b, ci=%b, sum=%b, cout=%b,  ERROR!!!", a,b,ci,sum,cout);  $finish; end
	@(posedge clk)
		a = 1'b1;
		b = 1'b0;
		ci = 1'b0;
		@(posedge clk)
			if ((sum != 1)|(cout != 0)|(sum===1'bz)|(cout===1'bz)|(sum===1'bx)|(cout===1'bx)) begin 
			$display($time, ,"a=%b, b=%b, ci=%b, sum=%b, cout=%b,  ERROR!!!", a,b,ci,sum,cout);  $finish; end
	@(posedge clk)
		a = 1'b1;
		b = 1'b0;
		ci = 1'b1;
		@(posedge clk)
			if ((sum != 0)|(cout != 1)|(sum===1'bz)|(cout===1'bz)|(sum===1'bx)|(cout===1'bx)) begin 
			$display($time, ,"a=%b, b=%b, ci=%b, sum=%b, cout=%b,  ERROR!!!", a,b,ci,sum,cout);  $finish; end
	@(posedge clk)
		a = 1'b1;
		b = 1'b1;
		ci = 1'b0;
		@(posedge clk)
			if ((sum != 0)|(cout != 1)|(sum===1'bz)|(cout===1'bz)|(sum===1'bx)|(cout===1'bx)) begin 
			$display($time, ,"a=%b, b=%b, ci=%b, sum=%b, cout=%b,  ERROR!!!", a,b,ci,sum,cout);  $finish; end
	@(posedge clk)
		a = 1'b1;
		b = 1'b1;
		ci = 1'b1;
		@(posedge clk)
			if ((sum != 1)|(cout != 1)|(sum===1'bz)|(cout===1'bz)|(sum===1'bx)|(cout===1'bx)) begin 
			$display($time, ,"a=%b, b=%b, ci=%b, sum=%b, cout=%b,  ERROR!!!", a,b,ci,sum,cout);  $finish; end
	@(posedge clk)
		$display("\n");
		$display("***********************");
		$display("function test pass !!");
		$display("***********************");
		$display("\n");
		$finish;

end


initial
begin
	//$fsdbDumpfile("fa.fsdb");
	//$fsdbDumpvars;

    $dumpfile("fa.vcd");   // The VCD Database
    $dumpvars;
end



endmodule

lab1-1/fa.vcd
$date
	Tue Mar 17 21:00:07 2026
$end
$version
	Icarus Verilog
$end
$timescale
	10ps
$end
$scope module fa_test $end
$var wire 1 ! sum $end
$var wire 1 " cout $end
$var reg 1 # a $end
$var reg 1 $ b $end
$var reg 1 % ci $end
$var reg 1 & clk $end
$scope module i_fa $end
$var wire 1 # a $end
$var wire 1 $ b $end
$var wire 1 % ci $end
$var wire 1 " cout $end
$var wire 1 ! sum $end
$var wire 1 ' s1 $end
$var wire 1 ( c2 $end
$var wire 1 ) c1 $end
$scope module ha1 $end
$var wire 1 # a $end
$var wire 1 $ b $end
$var wire 1 ) cout $end
$var wire 1 ' sum $end
$upscope $end
$scope module ha2 $end
$var wire 1 ' a $end
$var wire 1 % b $end
$var wire 1 ( cout $end
$var wire 1 ! sum $end
$upscope $end
$upscope $end
$upscope $end
$enddefinitions $end
$comment Show the parameter values. $end
$dumpall
$end
#0
$dumpvars
x)
x(
x'
0&
x%
x$
x#
x"
x!
$end
#200
0"
0!
0(
0'
0)
0%
0$
0#
1&
#400
0&
#600
1&
#800
0&
#1000
1!
1%
1&
#1200
0&
#1400
1&
#1600
0&
#1800
1'
0%
1$
1&
#2000
0&
#2200
1&
#2400
0&
#2600
1"
0!
1(
1%
1&
#2800
0&
#3000
1&
#3200
0&
#3400
0"
1!
0(
0%
0$
1#
1&
#3600
0&
#3800
1&
#4000
0&
#4200
1"
0!
1(
1%
1&
#4400
0&
#4600
1&
#4800
0&
#5000
0(
0'
1)
0%
1$
1&
#5200
0&
#5400
1&
#5600
0&
#5800
1!
1%
1&
